data_integration_babel/__init__.py
data_integration_babel/database_writer.py
data_integration_babel/receiver.py
data_integration_babel-0.5.dist-info/METADATA
data_integration_babel-0.5.dist-info/WHEEL
data_integration_babel-0.5.dist-info/top_level.txt
data_integration_babel-0.5.dist-info/RECORD
